amans/__init__.py
amans/timesq.py
amans-0.0.1.dist-info/METADATA
amans-0.0.1.dist-info/WHEEL
amans-0.0.1.dist-info/top_level.txt
amans-0.0.1.dist-info/RECORD
