Metadata-Version: 2.1
Name: amans
Version: 0.0.1
Summary: Print date time exmaple
Home-page: https://github.com/amansrivastav-bytequests/system-information
Author: Aman Srivastav
Author-email: amansrivastav.bytequests@gmail.com
License: BSD 2-clause
Classifier: Development Status :: 1 - Planning
Classifier: Intended Audience :: Science/Research
Classifier: License :: OSI Approved :: BSD License
Classifier: Operating System :: POSIX :: Linux
Classifier: Programming Language :: Python :: 3.5
Requires-Python: >=3.6
